{
  "name": "Universal Emoji Parser",
  "dockerComposeFile": "../docker/local/docker-compose.yaml",
  "service": "uemojiparser",
  "workspaceFolder": "/app",
  "runServices": ["uemojiparser"],
  "customizations": {
    "settings": {
      "terminal.integrated.shell.linux": "/bin/bash"
    },
    "vscode": {
      "extensions": [
        "VisualStudioExptTeam.vscodeintellicode",
        "swyphcosmo.spellchecker",
        "streetsidesoftware.code-spell-checker",
        "donjayamanne.githistory",
        "vscode-icons-team.vscode-icons",
        "shardulm94.trailing-spaces",
        "esbenp.prettier-vscode",
        "ms-vscode.vscode-typescript-tslint-plugin",
        "compulim.vscode-mocha",
        "hbenl.vscode-mocha-test-adapter",
        "dbaeumer.vscode-eslint",
        "GitHub.copilot",
        "me-dutour-mathieu.vscode-github-actions"
      ]
    }
  }
}
